{
	"groups": [
		{
			"keys": "button_down_png,button_up_png,checkbox_select_disabled_png,checkbox_select_down_png,checkbox_select_up_png,checkbox_unselect_png,selected_png,border_png,header_png,thumb_pb_png,track_pb_png,radiobutton_select_disabled_png,radiobutton_select_down_png,radiobutton_select_up_png,radiobutton_unselect_png,roundthumb_png,track_sb_png,thumb_png,track_png,tracklight_png,handle_png,off_png,on_png,maskbg_png,black_png,loadingbg_png,buff_json,hurt_json,skill_json,target_select_json,char_json,battle_json,battle_enemy_json,skill_icon_attack_png,gameEui_json,Swordsman_portrait_png,Dragon_portrait_png,card_info_json",
			"name": "preload"
		},
		{
			"keys": "bg_json,Dragon_db_ske_json,Dragon_db_tex_json,Dragon_db_tex_png,Swordsman_db_ske_json,Swordsman_db_tex_json,Swordsman_db_tex_png",
			"name": "assets"
		},
		{
			"keys": "cardbg_png,selfSelectChar_png,enemySelectChar_png,infobg_png,fireParticle_json,fireParticle_png,lifebar_jpg,lifebarbg_jpg,bufficontest_png",
			"name": "battlecommon"
		}
	],
	"resources": [
		{
			"url": "assets/CheckBox/checkbox_select_disabled.png",
			"type": "image",
			"name": "checkbox_select_disabled_png"
		},
		{
			"url": "assets/CheckBox/checkbox_select_down.png",
			"type": "image",
			"name": "checkbox_select_down_png"
		},
		{
			"url": "assets/CheckBox/checkbox_select_up.png",
			"type": "image",
			"name": "checkbox_select_up_png"
		},
		{
			"url": "assets/CheckBox/checkbox_unselect.png",
			"type": "image",
			"name": "checkbox_unselect_png"
		},
		{
			"url": "assets/ItemRenderer/selected.png",
			"type": "image",
			"name": "selected_png"
		},
		{
			"url": "assets/Panel/border.png",
			"type": "image",
			"name": "border_png"
		},
		{
			"url": "assets/Panel/header.png",
			"type": "image",
			"name": "header_png"
		},
		{
			"url": "assets/RadioButton/radiobutton_select_disabled.png",
			"type": "image",
			"name": "radiobutton_select_disabled_png"
		},
		{
			"url": "assets/RadioButton/radiobutton_select_down.png",
			"type": "image",
			"name": "radiobutton_select_down_png"
		},
		{
			"url": "assets/RadioButton/radiobutton_select_up.png",
			"type": "image",
			"name": "radiobutton_select_up_png"
		},
		{
			"url": "assets/RadioButton/radiobutton_unselect.png",
			"type": "image",
			"name": "radiobutton_unselect_png"
		},
		{
			"url": "assets/ScrollBar/roundthumb.png",
			"type": "image",
			"name": "roundthumb_png"
		},
		{
			"url": "assets/Slider/thumb.png",
			"type": "image",
			"name": "thumb_png"
		},
		{
			"url": "assets/Slider/track.png",
			"type": "image",
			"name": "track_png"
		},
		{
			"url": "assets/Slider/tracklight.png",
			"type": "image",
			"name": "tracklight_png"
		},
		{
			"url": "assets/ToggleSwitch/handle.png",
			"type": "image",
			"name": "handle_png"
		},
		{
			"url": "assets/ToggleSwitch/off.png",
			"type": "image",
			"name": "off_png"
		},
		{
			"url": "assets/ToggleSwitch/on.png",
			"type": "image",
			"name": "on_png"
		},
		{
			"url": "assets/Button/button_down.png",
			"type": "image",
			"name": "button_down_png"
		},
		{
			"url": "assets/Button/button_up.png",
			"type": "image",
			"name": "button_up_png"
		},
		{
			"url": "assets/ProgressBar/thumb_pb.png",
			"type": "image",
			"name": "thumb_pb_png"
		},
		{
			"url": "assets/ProgressBar/track_pb.png",
			"type": "image",
			"name": "track_pb_png"
		},
		{
			"url": "assets/ScrollBar/track_sb.png",
			"type": "image",
			"name": "track_sb_png"
		},
		{
			"url": "battle/battlebg/background.json",
			"type": "sheet",
			"name": "bg_json",
			"subkeys": "-1_png,-2_png,0_png,1_png"
		},
		{
			"url": "battle/dbs/Dragon/Dragon_db_tex.png",
			"type": "image",
			"name": "Dragon_db_tex_png"
		},
		{
			"url": "battle/dbs/Swordsman/Swordsman_db_tex.png",
			"type": "image",
			"name": "Swordsman_db_tex_png"
		},
		{
			"url": "battle/dbs/Dragon/Dragon_db_tex.json",
			"type": "json",
			"name": "Dragon_db_tex_json"
		},
		{
			"url": "battle/dbs/Dragon/Dragon_db_ske.json",
			"type": "json",
			"name": "Dragon_db_ske_json"
		},
		{
			"url": "battle/dbs/Swordsman/Swordsman_db_ske.json",
			"type": "json",
			"name": "Swordsman_db_ske_json"
		},
		{
			"url": "battle/dbs/Swordsman/Swordsman_db_tex.json",
			"type": "json",
			"name": "Swordsman_db_tex_json"
		},
		{
			"url": "battle/common/cardbg.png",
			"type": "image",
			"name": "cardbg_png"
		},
		{
			"url": "battle/common/enemySelectChar.png",
			"type": "image",
			"name": "enemySelectChar_png"
		},
		{
			"url": "battle/common/selfSelectChar.png",
			"type": "image",
			"name": "selfSelectChar_png"
		},
		{
			"url": "battle/common/infobg.png",
			"type": "image",
			"name": "infobg_png",
			"scale9grid": "11,10,40,7"
		},
		{
			"url": "battle/common/fireParticle.json",
			"type": "json",
			"name": "fireParticle_json"
		},
		{
			"url": "battle/common/fireParticle.png",
			"type": "image",
			"name": "fireParticle_png"
		},
		{
			"url": "battle/common/lifebar.jpg",
			"type": "image",
			"name": "lifebar_jpg"
		},
		{
			"url": "battle/common/lifebarbg.jpg",
			"type": "image",
			"name": "lifebarbg_jpg"
		},
		{
			"url": "common/maskbg.png",
			"type": "image",
			"name": "maskbg_png"
		},
		{
			"url": "common/black.png",
			"type": "image",
			"name": "black_png"
		},
		{
			"url": "common/loadingbg.png",
			"type": "image",
			"name": "loadingbg_png"
		},
		{
			"url": "battle/common/bufficontest.png",
			"type": "image",
			"name": "bufficontest_png"
		},
		{
			"url": "json_config/buff.json",
			"type": "json",
			"name": "buff_json"
		},
		{
			"url": "json_config/hurt.json",
			"type": "json",
			"name": "hurt_json"
		},
		{
			"url": "json_config/skill.json",
			"type": "json",
			"name": "skill_json"
		},
		{
			"url": "json_config/target_select.json",
			"type": "json",
			"name": "target_select_json"
		},
		{
			"url": "json_config/char.json",
			"type": "json",
			"name": "char_json"
		},
		{
			"url": "json_config/battle.json",
			"type": "json",
			"name": "battle_json"
		},
		{
			"url": "json_config/battle_enemy.json",
			"type": "json",
			"name": "battle_enemy_json"
		},
		{
			"url": "skillicon/skill_icon_attack.png",
			"type": "image",
			"name": "skill_icon_attack_png"
		},
		{
			"url": "gameEui.json",
			"type": "json",
			"name": "gameEui_json"
		},
		{
			"url": "portrait/Dragon_portrait.png",
			"type": "image",
			"name": "Dragon_portrait_png"
		},
		{
			"url": "portrait/Swordsman_portrait.png",
			"type": "image",
			"name": "Swordsman_portrait_png"
		},
		{
			"name": "card_info_json",
			"type": "json",
			"url": "json_config/card_info.json"
		}
	]
}